{
    "@context": "/contexts/Card",
    "@id": "/cards/ALT_EOLE_B_YZ_115_U_3991",
    "@type": "Card",
    "allImagePath": {
        "de-de": "",
        "en-us": "https://altered-prod-eu.s3.amazonaws.com/Art/EOLE/CARDS/ALT_EOLE_B_YZ_115/UNIQUE/JPG/en_US/60112c185582f8aca18e8ac2a334bcd0.jpg",
        "es-es": "",
        "fr-fr": "https://altered-prod-eu.s3.amazonaws.com/Art/EOLE/CARDS/ALT_EOLE_B_YZ_115/UNIQUE/JPG/fr_FR/61149b0e7bbbcd52d3b2e3980e80b997.jpg",
        "it-it": ""
    },
    "assets": {
        "WEB": [
            "https://altered-prod-eu.s3.amazonaws.com/Art/EOLE/CARDS/ALT_EOLE_B_YZ_115/WEB_6d4917f730620b910e844b76d58f29cd",
            "https://altered-prod-eu.s3.amazonaws.com/Art/EOLE/CARDS/ALT_EOLE_B_YZ_115/WEB_28b87528f710a8b999d1f2f497c81f38",
            "https://altered-prod-eu.s3.amazonaws.com/Art/EOLE/CARDS/ALT_EOLE_B_YZ_115/WEB_6071c867ba2c54d40e83fac00539369d"
        ]
    },
    "cardSet": {
        "@id": "/card_sets/EOLE",
        "@type": "CardSet",
        "id": "01K9YWHXF2T6GJJDWAK333TJGV",
        "name": "Roots of Corruption",
        "reference": "EOLE"
    },
    "cardSubTypes": [
        {
            "@id": "/.well-known/genid/b7719f5d56cefd9af896",
            "@type": "CardSubType",
            "id": "01KA0YFDBT5GF5YYW6RP9VJ0GB",
            "name": "Corruption",
            "reference": "CORRUPTION"
        }
    ],
    "cardType": {
        "@id": "/card_types/01H19NWA92A4ERAC4ATMSZNASS",
        "@type": "CardType",
        "id": "01H19NWA92A4ERAC4ATMSZNASS",
        "name": "Character",
        "reference": "CHARACTER"
    },
    "elements": {
        "FOREST_POWER": "3",
        "MAIN_COST": "3",
        "MAIN_EFFECT": "{J} Do this once for each card with my name in your discard pile: Draw a card.  When I go to Reserve from the Expedition zone — []Reveal the top card of your deck. If it's a Spell, draw it.",
        "MOUNTAIN_POWER": "3",
        "OCEAN_POWER": "3",
        "RECALL_COST": "3"
    },
    "id": "74JC60YR3G9BFV3JDVJJFXN971",
    "imagePath": "https://altered-prod-eu.s3.amazonaws.com/Art/EOLE/CARDS/ALT_EOLE_B_YZ_115/UNIQUE/JPG/en_US/60112c185582f8aca18e8ac2a334bcd0.jpg",
    "isBanned": false,
    "isErrated": false,
    "isOwnerless": false,
    "isParentSerialized": false,
    "isSerialized": false,
    "isSuspended": false,
    "loreEntries": [],
    "lowerPrice": 0,
    "mainFaction": {
        "@id": "/factions/YZ",
        "@type": "Faction",
        "color": "#764891",
        "id": "01GE7AC9WEQKW1Y1BF8SCY7459",
        "name": "Yzmir",
        "reference": "YZ"
    },
    "name": "Stigma of Fallacy",
    "qrUrlDetail": "https://qr.altered.gg/ALT_EOLE_B_YZ_115_U_3991",
    "rarity": {
        "@id": "/.well-known/genid/173e4c4d83b96b4844b3",
        "@type": "Rarity",
        "id": "01GE7AC9X35JXEQZJBBD6E4BKW",
        "name": "Unique",
        "reference": "UNIQUE"
    },
    "reference": "ALT_EOLE_B_YZ_115_U_3991",
    "translations": {
        "de-de": {
            "@context": "/contexts/Card",
            "@id": "/cards/ALT_EOLE_B_YZ_115_U_3991",
            "@type": "Card",
            "allImagePath": {
                "de-de": "",
                "en-us": "https://altered-prod-eu.s3.amazonaws.com/Art/EOLE/CARDS/ALT_EOLE_B_YZ_115/UNIQUE/JPG/en_US/60112c185582f8aca18e8ac2a334bcd0.jpg",
                "es-es": "",
                "fr-fr": "https://altered-prod-eu.s3.amazonaws.com/Art/EOLE/CARDS/ALT_EOLE_B_YZ_115/UNIQUE/JPG/fr_FR/61149b0e7bbbcd52d3b2e3980e80b997.jpg",
                "it-it": ""
            },
            "assets": {
                "WEB": [
                    "https://altered-prod-eu.s3.amazonaws.com/Art/EOLE/CARDS/ALT_EOLE_B_YZ_115/WEB_6d4917f730620b910e844b76d58f29cd",
                    "https://altered-prod-eu.s3.amazonaws.com/Art/EOLE/CARDS/ALT_EOLE_B_YZ_115/WEB_28b87528f710a8b999d1f2f497c81f38",
                    "https://altered-prod-eu.s3.amazonaws.com/Art/EOLE/CARDS/ALT_EOLE_B_YZ_115/WEB_6071c867ba2c54d40e83fac00539369d"
                ]
            },
            "cardSet": {
                "@id": "/card_sets/EOLE",
                "@type": "CardSet",
                "id": "01K9YWHXF2T6GJJDWAK333TJGV",
                "name": "Roots of Corruption",
                "reference": "EOLE"
            },
            "cardSubTypes": [
                {
                    "@id": "/.well-known/genid/89557aea16c5e56b6635",
                    "@type": "CardSubType",
                    "id": "01KA0YFDBT5GF5YYW6RP9VJ0GB",
                    "name": "Verfall",
                    "reference": "CORRUPTION"
                }
            ],
            "cardType": {
                "@id": "/card_types/01H19NWA92A4ERAC4ATMSZNASS",
                "@type": "CardType",
                "id": "01H19NWA92A4ERAC4ATMSZNASS",
                "name": "Charakter",
                "reference": "CHARACTER"
            },
            "elements": {
                "FOREST_POWER": "3",
                "MAIN_COST": "3",
                "MAIN_EFFECT": "{J} Tue dies einmal für jede Karte mit meinem Namen auf deinem Ablagestapel: Ziehe eine Karte.  Wenn ich aus der Expeditionszone in die Reserve gehe — []Decke die oberste Karte deines Decks auf. Falls es ein Zauber ist, ziehe sie.",
                "MOUNTAIN_POWER": "3",
                "OCEAN_POWER": "3",
                "RECALL_COST": "3"
            },
            "id": "74JC60YR3G9BFV3JDVJJFXN971",
            "imagePath": "https://altered-prod-eu.s3.amazonaws.com/Art/EOLE/CARDS/ALT_EOLE_B_YZ_115/UNIQUE/JPG/en_US/60112c185582f8aca18e8ac2a334bcd0.jpg",
            "isBanned": false,
            "isErrated": false,
            "isOwnerless": false,
            "isParentSerialized": false,
            "isSerialized": false,
            "isSuspended": false,
            "loreEntries": [],
            "lowerPrice": 0,
            "mainFaction": {
                "@id": "/factions/YZ",
                "@type": "Faction",
                "color": "#764891",
                "id": "01GE7AC9WEQKW1Y1BF8SCY7459",
                "name": "Yzmir",
                "reference": "YZ"
            },
            "name": "Stigma der Täuschung",
            "qrUrlDetail": "https://qr.altered.gg/ALT_EOLE_B_YZ_115_U_3991",
            "rarity": {
                "@id": "/.well-known/genid/7712e67660a89a205390",
                "@type": "Rarity",
                "id": "01GE7AC9X35JXEQZJBBD6E4BKW",
                "name": "Unique",
                "reference": "UNIQUE"
            },
            "reference": "ALT_EOLE_B_YZ_115_U_3991"
        },
        "es-es": {
            "@context": "/contexts/Card",
            "@id": "/cards/ALT_EOLE_B_YZ_115_U_3991",
            "@type": "Card",
            "allImagePath": {
                "de-de": "",
                "en-us": "https://altered-prod-eu.s3.amazonaws.com/Art/EOLE/CARDS/ALT_EOLE_B_YZ_115/UNIQUE/JPG/en_US/60112c185582f8aca18e8ac2a334bcd0.jpg",
                "es-es": "",
                "fr-fr": "https://altered-prod-eu.s3.amazonaws.com/Art/EOLE/CARDS/ALT_EOLE_B_YZ_115/UNIQUE/JPG/fr_FR/61149b0e7bbbcd52d3b2e3980e80b997.jpg",
                "it-it": ""
            },
            "assets": {
                "WEB": [
                    "https://altered-prod-eu.s3.amazonaws.com/Art/EOLE/CARDS/ALT_EOLE_B_YZ_115/WEB_6d4917f730620b910e844b76d58f29cd",
                    "https://altered-prod-eu.s3.amazonaws.com/Art/EOLE/CARDS/ALT_EOLE_B_YZ_115/WEB_28b87528f710a8b999d1f2f497c81f38",
                    "https://altered-prod-eu.s3.amazonaws.com/Art/EOLE/CARDS/ALT_EOLE_B_YZ_115/WEB_6071c867ba2c54d40e83fac00539369d"
                ]
            },
            "cardSet": {
                "@id": "/card_sets/EOLE",
                "@type": "CardSet",
                "id": "01K9YWHXF2T6GJJDWAK333TJGV",
                "name": "Roots of Corruption",
                "reference": "EOLE"
            },
            "cardSubTypes": [
                {
                    "@id": "/.well-known/genid/1b77a59302b798bbf2b2",
                    "@type": "CardSubType",
                    "id": "01KA0YFDBT5GF5YYW6RP9VJ0GB",
                    "name": "Corrupción",
                    "reference": "CORRUPTION"
                }
            ],
            "cardType": {
                "@id": "/card_types/01H19NWA92A4ERAC4ATMSZNASS",
                "@type": "CardType",
                "id": "01H19NWA92A4ERAC4ATMSZNASS",
                "name": "Personaje",
                "reference": "CHARACTER"
            },
            "elements": {
                "FOREST_POWER": "3",
                "MAIN_COST": "3",
                "MAIN_EFFECT": "{J} Haz esto una vez por cada carta con mi nombre en tu pila de descartes: Roba una carta.  Cuando vaya a la reserva desde la zona de expedición — []Revela la primera carta de tu mazo. Si es un hechizo, róbala.",
                "MOUNTAIN_POWER": "3",
                "OCEAN_POWER": "3",
                "RECALL_COST": "3"
            },
            "id": "74JC60YR3G9BFV3JDVJJFXN971",
            "imagePath": "https://altered-prod-eu.s3.amazonaws.com/Art/EOLE/CARDS/ALT_EOLE_B_YZ_115/UNIQUE/JPG/en_US/60112c185582f8aca18e8ac2a334bcd0.jpg",
            "isBanned": false,
            "isErrated": false,
            "isOwnerless": false,
            "isParentSerialized": false,
            "isSerialized": false,
            "isSuspended": false,
            "loreEntries": [],
            "lowerPrice": 0,
            "mainFaction": {
                "@id": "/factions/YZ",
                "@type": "Faction",
                "color": "#764891",
                "id": "01GE7AC9WEQKW1Y1BF8SCY7459",
                "name": "Yzmir",
                "reference": "YZ"
            },
            "name": "Estigma de la falacia",
            "qrUrlDetail": "https://qr.altered.gg/ALT_EOLE_B_YZ_115_U_3991",
            "rarity": {
                "@id": "/.well-known/genid/3b1908b22f7020457bba",
                "@type": "Rarity",
                "id": "01GE7AC9X35JXEQZJBBD6E4BKW",
                "name": "Unique",
                "reference": "UNIQUE"
            },
            "reference": "ALT_EOLE_B_YZ_115_U_3991"
        },
        "fr-fr": {
            "@context": "/contexts/Card",
            "@id": "/cards/ALT_EOLE_B_YZ_115_U_3991",
            "@type": "Card",
            "allImagePath": {
                "de-de": "",
                "en-us": "https://altered-prod-eu.s3.amazonaws.com/Art/EOLE/CARDS/ALT_EOLE_B_YZ_115/UNIQUE/JPG/en_US/60112c185582f8aca18e8ac2a334bcd0.jpg",
                "es-es": "",
                "fr-fr": "https://altered-prod-eu.s3.amazonaws.com/Art/EOLE/CARDS/ALT_EOLE_B_YZ_115/UNIQUE/JPG/fr_FR/61149b0e7bbbcd52d3b2e3980e80b997.jpg",
                "it-it": ""
            },
            "assets": {
                "WEB": [
                    "https://altered-prod-eu.s3.amazonaws.com/Art/EOLE/CARDS/ALT_EOLE_B_YZ_115/WEB_6d4917f730620b910e844b76d58f29cd",
                    "https://altered-prod-eu.s3.amazonaws.com/Art/EOLE/CARDS/ALT_EOLE_B_YZ_115/WEB_28b87528f710a8b999d1f2f497c81f38",
                    "https://altered-prod-eu.s3.amazonaws.com/Art/EOLE/CARDS/ALT_EOLE_B_YZ_115/WEB_6071c867ba2c54d40e83fac00539369d"
                ]
            },
            "cardSet": {
                "@id": "/card_sets/EOLE",
                "@type": "CardSet",
                "id": "01K9YWHXF2T6GJJDWAK333TJGV",
                "name": "Les Racines de la Corruption",
                "reference": "EOLE"
            },
            "cardSubTypes": [
                {
                    "@id": "/.well-known/genid/a47477f074307612862f",
                    "@type": "CardSubType",
                    "id": "01KA0YFDBT5GF5YYW6RP9VJ0GB",
                    "name": "Corruption",
                    "reference": "CORRUPTION"
                }
            ],
            "cardType": {
                "@id": "/card_types/01H19NWA92A4ERAC4ATMSZNASS",
                "@type": "CardType",
                "id": "01H19NWA92A4ERAC4ATMSZNASS",
                "name": "Personnage",
                "reference": "CHARACTER"
            },
            "elements": {
                "FOREST_POWER": "3",
                "MAIN_COST": "3",
                "MAIN_EFFECT": "{J} Faites cela une fois pour chaque carte avec mon nom dans votre défausse : Piochez une carte.  Lorsque je vais en Réserve depuis la zone d'Expédition — []Révélez la première carte de votre deck. Si c'est un Sort, piochez-la.",
                "MOUNTAIN_POWER": "3",
                "OCEAN_POWER": "3",
                "RECALL_COST": "3"
            },
            "id": "74JC60YR3G9BFV3JDVJJFXN971",
            "imagePath": "https://altered-prod-eu.s3.amazonaws.com/Art/EOLE/CARDS/ALT_EOLE_B_YZ_115/UNIQUE/JPG/fr_FR/61149b0e7bbbcd52d3b2e3980e80b997.jpg",
            "isBanned": false,
            "isErrated": false,
            "isOwnerless": false,
            "isParentSerialized": false,
            "isSerialized": false,
            "isSuspended": false,
            "loreEntries": [],
            "lowerPrice": 0,
            "mainFaction": {
                "@id": "/factions/YZ",
                "@type": "Faction",
                "color": "#764891",
                "id": "01GE7AC9WEQKW1Y1BF8SCY7459",
                "name": "Yzmir",
                "reference": "YZ"
            },
            "name": "Stigmate de la Duperie",
            "qrUrlDetail": "https://qr.altered.gg/ALT_EOLE_B_YZ_115_U_3991",
            "rarity": {
                "@id": "/.well-known/genid/2333d959a1e968091fef",
                "@type": "Rarity",
                "id": "01GE7AC9X35JXEQZJBBD6E4BKW",
                "name": "Unique",
                "reference": "UNIQUE"
            },
            "reference": "ALT_EOLE_B_YZ_115_U_3991"
        },
        "it-it": {
            "@context": "/contexts/Card",
            "@id": "/cards/ALT_EOLE_B_YZ_115_U_3991",
            "@type": "Card",
            "allImagePath": {
                "de-de": "",
                "en-us": "https://altered-prod-eu.s3.amazonaws.com/Art/EOLE/CARDS/ALT_EOLE_B_YZ_115/UNIQUE/JPG/en_US/60112c185582f8aca18e8ac2a334bcd0.jpg",
                "es-es": "",
                "fr-fr": "https://altered-prod-eu.s3.amazonaws.com/Art/EOLE/CARDS/ALT_EOLE_B_YZ_115/UNIQUE/JPG/fr_FR/61149b0e7bbbcd52d3b2e3980e80b997.jpg",
                "it-it": ""
            },
            "assets": {
                "WEB": [
                    "https://altered-prod-eu.s3.amazonaws.com/Art/EOLE/CARDS/ALT_EOLE_B_YZ_115/WEB_6d4917f730620b910e844b76d58f29cd",
                    "https://altered-prod-eu.s3.amazonaws.com/Art/EOLE/CARDS/ALT_EOLE_B_YZ_115/WEB_28b87528f710a8b999d1f2f497c81f38",
                    "https://altered-prod-eu.s3.amazonaws.com/Art/EOLE/CARDS/ALT_EOLE_B_YZ_115/WEB_6071c867ba2c54d40e83fac00539369d"
                ]
            },
            "cardSet": {
                "@id": "/card_sets/EOLE",
                "@type": "CardSet",
                "id": "01K9YWHXF2T6GJJDWAK333TJGV",
                "name": "Roots of Corruption",
                "reference": "EOLE"
            },
            "cardSubTypes": [
                {
                    "@id": "/.well-known/genid/83776fa2cfb0f480eac5",
                    "@type": "CardSubType",
                    "id": "01KA0YFDBT5GF5YYW6RP9VJ0GB",
                    "name": "Corruzione",
                    "reference": "CORRUPTION"
                }
            ],
            "cardType": {
                "@id": "/card_types/01H19NWA92A4ERAC4ATMSZNASS",
                "@type": "CardType",
                "id": "01H19NWA92A4ERAC4ATMSZNASS",
                "name": "Personaggio",
                "reference": "CHARACTER"
            },
            "elements": {
                "FOREST_POWER": "3",
                "MAIN_COST": "3",
                "MAIN_EFFECT": "{J} Esegui questa azione una volta per ogni carta con il mio nome nella tua pila degli scarti: Pesca una carta.  Quando vado nella Riserva dall'area delle spedizioni — []Rivela la prima carta del tuo mazzo. Se è un incantesimo, pescala.",
                "MOUNTAIN_POWER": "3",
                "OCEAN_POWER": "3",
                "RECALL_COST": "3"
            },
            "id": "74JC60YR3G9BFV3JDVJJFXN971",
            "imagePath": "https://altered-prod-eu.s3.amazonaws.com/Art/EOLE/CARDS/ALT_EOLE_B_YZ_115/UNIQUE/JPG/en_US/60112c185582f8aca18e8ac2a334bcd0.jpg",
            "isBanned": false,
            "isErrated": false,
            "isOwnerless": false,
            "isParentSerialized": false,
            "isSerialized": false,
            "isSuspended": false,
            "loreEntries": [],
            "lowerPrice": 0,
            "mainFaction": {
                "@id": "/factions/YZ",
                "@type": "Faction",
                "color": "#764891",
                "id": "01GE7AC9WEQKW1Y1BF8SCY7459",
                "name": "Yzmir",
                "reference": "YZ"
            },
            "name": "Stigma della Fallacia",
            "qrUrlDetail": "https://qr.altered.gg/ALT_EOLE_B_YZ_115_U_3991",
            "rarity": {
                "@id": "/.well-known/genid/a29616fe3332b259be5a",
                "@type": "Rarity",
                "id": "01GE7AC9X35JXEQZJBBD6E4BKW",
                "name": "Unique",
                "reference": "UNIQUE"
            },
            "reference": "ALT_EOLE_B_YZ_115_U_3991"
        }
    }
}