{
    "@context": "/contexts/Card",
    "@id": "/cards/ALT_COREKS_B_YZ_16_U_2175",
    "@type": "Card",
    "allImagePath": {
        "de-de": "https://altered-prod-eu.s3.amazonaws.com/Art/COREKS/CARDS/ALT_CORE_B_YZ_16/UNIQUE/JPG/de_DE/bee60305fe6d43542cf54c3c3b3971cf.jpg",
        "en-us": "https://altered-prod-eu.s3.amazonaws.com/Art/COREKS/CARDS/ALT_CORE_B_YZ_16/UNIQUE/JPG/en_US/a5dae3cbb317c8f105badf061797866e.jpg",
        "es-es": "https://altered-prod-eu.s3.amazonaws.com/Art/COREKS/CARDS/ALT_CORE_B_YZ_16/UNIQUE/JPG/es_ES/426b49865e8ad3a22c38ff84c6021a1b.jpg",
        "fr-fr": "https://altered-prod-eu.s3.amazonaws.com/Art/COREKS/CARDS/ALT_CORE_B_YZ_16/UNIQUE/JPG/fr_FR/a48b8ac0d20ec12a38ba13881e726d18.jpg",
        "it-it": "https://altered-prod-eu.s3.amazonaws.com/Art/COREKS/CARDS/ALT_CORE_B_YZ_16/UNIQUE/JPG/it_IT/87ee8069b7e5594af19431ae467664b6.jpg"
    },
    "assets": {
        "WEB": [
            "https://altered-prod-eu.s3.amazonaws.com/Art/CORE/CARDS/ALT_CORE_B_YZ_16/ALT_CORE_B_YZ_16_C_WEB.jpg",
            "https://altered-prod-eu.s3.amazonaws.com/Art/CORE/CARDS/ALT_CORE_B_YZ_16/ALT_CORE_B_YZ_16_R_WEB.jpg",
            "https://altered-prod-eu.s3.amazonaws.com/Art/CORE/CARDS/ALT_CORE_B_YZ_16/ALT_CORE_B_YZ_16_U_WEB.jpg"
        ]
    },
    "cardRulings": [],
    "cardSet": {
        "@id": "/card_sets/COREKS",
        "@type": "CardSet",
        "id": "01HN5TWSSVYM93FHCEC3K8NNCM",
        "name": "Beyond the Gates - KS Edition",
        "reference": "COREKS"
    },
    "cardSubTypes": [
        {
            "@id": "/.well-known/genid/ffc5cac781924f892b72",
            "@type": "CardSubType",
            "id": "01HKAGQWDFDGS8YVZGW98BVV9D",
            "name": "Citizen",
            "reference": "CITIZEN"
        }
    ],
    "cardType": {
        "@id": "/card_types/01H19NWA92A4ERAC4ATMSZNASS",
        "@type": "CardType",
        "id": "01H19NWA92A4ERAC4ATMSZNASS",
        "name": "Character",
        "reference": "CHARACTER"
    },
    "elements": {
        "FOREST_POWER": "4",
        "MAIN_COST": "4",
        "MAIN_EFFECT": "{J} You may put a card from your hand in Reserve. If it's a Spell: You may send to Reserve target Character with Hand Cost {3} or less.  {J} If there's a card in your Landmarks: Target Character gains 1 boost.",
        "MOUNTAIN_POWER": "3",
        "OCEAN_POWER": "1",
        "RECALL_COST": "4"
    },
    "id": "75DM9VAHSZ8C8TXGBDB93PHWKZ",
    "isBanned": false,
    "isErrated": false,
    "isOwnerless": false,
    "isSuspended": false,
    "loreEntries": [],
    "lowerPrice": 0,
    "mainFaction": {
        "@id": "/factions/YZ",
        "@type": "Faction",
        "color": "#764891",
        "id": "01GE7AC9WEQKW1Y1BF8SCY7459",
        "name": "Yzmir",
        "reference": "YZ"
    },
    "name": "Dorothy Gale",
    "qrUrlDetail": "https://qr.altered.gg/ALT_COREKS_B_YZ_16_U_2175",
    "rarity": {
        "@id": "/.well-known/genid/ee7e5ab40f4e0c690f5d",
        "@type": "Rarity",
        "id": "01GE7AC9X35JXEQZJBBD6E4BKW",
        "name": "Unique",
        "reference": "UNIQUE"
    },
    "reference": "ALT_COREKS_B_YZ_16_U_2175",
    "translations": {
        "fr-fr": {
            "@context": "/contexts/Card",
            "@id": "/cards/ALT_COREKS_B_YZ_16_U_2175",
            "@type": "Card",
            "allImagePath": {
                "de-de": "https://altered-prod-eu.s3.amazonaws.com/Art/COREKS/CARDS/ALT_CORE_B_YZ_16/UNIQUE/JPG/de_DE/bee60305fe6d43542cf54c3c3b3971cf.jpg",
                "en-us": "https://altered-prod-eu.s3.amazonaws.com/Art/COREKS/CARDS/ALT_CORE_B_YZ_16/UNIQUE/JPG/en_US/a5dae3cbb317c8f105badf061797866e.jpg",
                "es-es": "https://altered-prod-eu.s3.amazonaws.com/Art/COREKS/CARDS/ALT_CORE_B_YZ_16/UNIQUE/JPG/es_ES/426b49865e8ad3a22c38ff84c6021a1b.jpg",
                "fr-fr": "https://altered-prod-eu.s3.amazonaws.com/Art/COREKS/CARDS/ALT_CORE_B_YZ_16/UNIQUE/JPG/fr_FR/a48b8ac0d20ec12a38ba13881e726d18.jpg",
                "it-it": "https://altered-prod-eu.s3.amazonaws.com/Art/COREKS/CARDS/ALT_CORE_B_YZ_16/UNIQUE/JPG/it_IT/87ee8069b7e5594af19431ae467664b6.jpg"
            },
            "assets": {
                "WEB": [
                    "https://altered-prod-eu.s3.amazonaws.com/Art/CORE/CARDS/ALT_CORE_B_YZ_16/ALT_CORE_B_YZ_16_C_WEB.jpg",
                    "https://altered-prod-eu.s3.amazonaws.com/Art/CORE/CARDS/ALT_CORE_B_YZ_16/ALT_CORE_B_YZ_16_R_WEB.jpg",
                    "https://altered-prod-eu.s3.amazonaws.com/Art/CORE/CARDS/ALT_CORE_B_YZ_16/ALT_CORE_B_YZ_16_U_WEB.jpg"
                ]
            },
            "cardRulings": [],
            "cardSet": {
                "@id": "/card_sets/COREKS",
                "@type": "CardSet",
                "id": "01HN5TWSSVYM93FHCEC3K8NNCM",
                "name": "Au-delà des portes - Édition KS",
                "reference": "COREKS"
            },
            "cardSubTypes": [
                {
                    "@id": "/.well-known/genid/b53d0a2f815ed58b1ab0",
                    "@type": "CardSubType",
                    "id": "01HKAGQWDFDGS8YVZGW98BVV9D",
                    "name": "Citoyen",
                    "reference": "CITIZEN"
                }
            ],
            "cardType": {
                "@id": "/card_types/01H19NWA92A4ERAC4ATMSZNASS",
                "@type": "CardType",
                "id": "01H19NWA92A4ERAC4ATMSZNASS",
                "name": "Personnage",
                "reference": "CHARACTER"
            },
            "elements": {
                "FOREST_POWER": "4",
                "MAIN_COST": "4",
                "MAIN_EFFECT": "{J} Vous pouvez mettre une carte de votre main en Réserve. Si c'est un Sort : Vous pouvez envoyer en Réserve un Personnage ciblé de Coût de Main {3} ou moins.  {J} S'il y a au moins une carte dans vos Repères : Un Personnage ciblé gagne 1 boost.",
                "MOUNTAIN_POWER": "3",
                "OCEAN_POWER": "1",
                "RECALL_COST": "4"
            },
            "id": "75DM9VAHSZ8C8TXGBDB93PHWKZ",
            "imagePath": "https://altered-prod-eu.s3.amazonaws.com/Art/COREKS/CARDS/ALT_CORE_B_YZ_16/UNIQUE/JPG/fr_FR/a48b8ac0d20ec12a38ba13881e726d18.jpg",
            "isBanned": false,
            "isErrated": false,
            "isOwnerless": false,
            "isSuspended": false,
            "loreEntries": [],
            "lowerPrice": 0,
            "mainFaction": {
                "@id": "/factions/YZ",
                "@type": "Faction",
                "color": "#764891",
                "id": "01GE7AC9WEQKW1Y1BF8SCY7459",
                "name": "Yzmir",
                "reference": "YZ"
            },
            "name": "Dorothy Gale",
            "qrUrlDetail": "https://qr.altered.gg/ALT_COREKS_B_YZ_16_U_2175",
            "rarity": {
                "@id": "/.well-known/genid/23cfa2a35701845a0d7d",
                "@type": "Rarity",
                "id": "01GE7AC9X35JXEQZJBBD6E4BKW",
                "name": "Unique",
                "reference": "UNIQUE"
            },
            "reference": "ALT_COREKS_B_YZ_16_U_2175"
        }
    }
}