{
    "@context": "/contexts/Card",
    "@id": "/cards/ALT_EOLE_B_AX_115_U_139",
    "@type": "Card",
    "allImagePath": {
        "de-de": "",
        "en-us": "https://altered-prod-eu.s3.amazonaws.com/Art/EOLE/CARDS/ALT_EOLE_B_AX_115/UNIQUE/JPG/en_US/ee4abd80beb562cb1a6458abed06b409.jpg",
        "es-es": "",
        "fr-fr": "https://altered-prod-eu.s3.amazonaws.com/Art/EOLE/CARDS/ALT_EOLE_B_AX_115/UNIQUE/JPG/fr_FR/1f3f15fd6e1a168a89ac07073b2ce27a.jpg",
        "it-it": ""
    },
    "assets": {
        "WEB": [
            "https://altered-prod-eu.s3.amazonaws.com/Art/EOLE/CARDS/ALT_EOLE_B_AX_115/WEB_016fd1f40f65ce5bdc99f4b762431413",
            "https://altered-prod-eu.s3.amazonaws.com/Art/EOLE/CARDS/ALT_EOLE_B_AX_115/WEB_c55528c8b3468d929bc8cba1fb00348b",
            "https://altered-prod-eu.s3.amazonaws.com/Art/EOLE/CARDS/ALT_EOLE_B_AX_115/WEB_289e3ffb45a1e9035052e04ae38e1c25"
        ]
    },
    "cardSet": {
        "@id": "/card_sets/EOLE",
        "@type": "CardSet",
        "id": "01K9YWHXF2T6GJJDWAK333TJGV",
        "name": "Roots of Corruption",
        "reference": "EOLE"
    },
    "cardSubTypes": [
        {
            "@id": "/.well-known/genid/77713551985417165429",
            "@type": "CardSubType",
            "id": "01HKAGPDNDJM76PRKTBB98Q0ZM",
            "name": "Robot",
            "reference": "ROBOT"
        },
        {
            "@id": "/.well-known/genid/f2651f9f70a5e419b68d",
            "@type": "CardSubType",
            "id": "01HKAGPAJFS4YDQVKY6AB16614",
            "name": "Deity",
            "reference": "DEITY"
        }
    ],
    "cardType": {
        "@id": "/card_types/01H19NWA92A4ERAC4ATMSZNASS",
        "@type": "CardType",
        "id": "01H19NWA92A4ERAC4ATMSZNASS",
        "name": "Character",
        "reference": "CHARACTER"
    },
    "elements": {
        "ECHO_EFFECT": "{D} : []The next Character played from your hand this turn activates one of its {r} abilities.",
        "FOREST_POWER": "5",
        "MAIN_COST": "4",
        "MAIN_EFFECT": "When you pass — If your hand is empty: Draw two cards.  When I leave the Expedition zone, if I was [[Fleeting]] — []Create two [Aerolith] tokens in your Landmarks.",
        "MOUNTAIN_POWER": "3",
        "OCEAN_POWER": "5",
        "RECALL_COST": "4"
    },
    "id": "4FSE7996C49KFV456HTYE0BQ3M",
    "imagePath": "https://altered-prod-eu.s3.amazonaws.com/Art/EOLE/CARDS/ALT_EOLE_B_AX_115/UNIQUE/JPG/en_US/ee4abd80beb562cb1a6458abed06b409.jpg",
    "isBanned": false,
    "isErrated": false,
    "isOwnerless": false,
    "isParentSerialized": false,
    "isSerialized": false,
    "isSuspended": false,
    "loreEntries": [],
    "lowerPrice": 0,
    "mainFaction": {
        "@id": "/factions/AX",
        "@type": "Faction",
        "color": "#8c432a",
        "id": "01GE7AC9XBG707G19F03A95TH1",
        "name": "Axiom",
        "reference": "AX"
    },
    "name": "Inari, Spirit of Industry",
    "qrUrlDetail": "https://qr.altered.gg/ALT_EOLE_B_AX_115_U_139",
    "rarity": {
        "@id": "/.well-known/genid/cbf52262cdbc11660d42",
        "@type": "Rarity",
        "id": "01GE7AC9X35JXEQZJBBD6E4BKW",
        "name": "Unique",
        "reference": "UNIQUE"
    },
    "reference": "ALT_EOLE_B_AX_115_U_139",
    "translations": {
        "de-de": {
            "@context": "/contexts/Card",
            "@id": "/cards/ALT_EOLE_B_AX_115_U_139",
            "@type": "Card",
            "allImagePath": {
                "de-de": "",
                "en-us": "https://altered-prod-eu.s3.amazonaws.com/Art/EOLE/CARDS/ALT_EOLE_B_AX_115/UNIQUE/JPG/en_US/ee4abd80beb562cb1a6458abed06b409.jpg",
                "es-es": "",
                "fr-fr": "https://altered-prod-eu.s3.amazonaws.com/Art/EOLE/CARDS/ALT_EOLE_B_AX_115/UNIQUE/JPG/fr_FR/1f3f15fd6e1a168a89ac07073b2ce27a.jpg",
                "it-it": ""
            },
            "assets": {
                "WEB": [
                    "https://altered-prod-eu.s3.amazonaws.com/Art/EOLE/CARDS/ALT_EOLE_B_AX_115/WEB_016fd1f40f65ce5bdc99f4b762431413",
                    "https://altered-prod-eu.s3.amazonaws.com/Art/EOLE/CARDS/ALT_EOLE_B_AX_115/WEB_c55528c8b3468d929bc8cba1fb00348b",
                    "https://altered-prod-eu.s3.amazonaws.com/Art/EOLE/CARDS/ALT_EOLE_B_AX_115/WEB_289e3ffb45a1e9035052e04ae38e1c25"
                ]
            },
            "cardSet": {
                "@id": "/card_sets/EOLE",
                "@type": "CardSet",
                "id": "01K9YWHXF2T6GJJDWAK333TJGV",
                "name": "Roots of Corruption",
                "reference": "EOLE"
            },
            "cardSubTypes": [
                {
                    "@id": "/.well-known/genid/3274569a786432b0506c",
                    "@type": "CardSubType",
                    "id": "01HKAGPDNDJM76PRKTBB98Q0ZM",
                    "name": "Roboter",
                    "reference": "ROBOT"
                },
                {
                    "@id": "/.well-known/genid/c65bcf958d295a10cb8e",
                    "@type": "CardSubType",
                    "id": "01HKAGPAJFS4YDQVKY6AB16614",
                    "name": "Gottheit",
                    "reference": "DEITY"
                }
            ],
            "cardType": {
                "@id": "/card_types/01H19NWA92A4ERAC4ATMSZNASS",
                "@type": "CardType",
                "id": "01H19NWA92A4ERAC4ATMSZNASS",
                "name": "Charakter",
                "reference": "CHARACTER"
            },
            "elements": {
                "ECHO_EFFECT": "{D} : []Der nächste Charakter, der in dieser Runde aus deiner Hand gespielt wird, aktiviert eine seiner {r} Fähigkeiten.",
                "FOREST_POWER": "5",
                "MAIN_COST": "4",
                "MAIN_EFFECT": "Wenn du passt — Falls deine Hand leer ist: Ziehe zwei Karten.  Wenn ich die Expeditionszone verlasse, falls ich [[Vergänglich]] war — []Erschaffe zwei [Aerolit]-Marken in deinem Wahrzeichen-Bereich.",
                "MOUNTAIN_POWER": "3",
                "OCEAN_POWER": "5",
                "RECALL_COST": "4"
            },
            "id": "4FSE7996C49KFV456HTYE0BQ3M",
            "imagePath": "https://altered-prod-eu.s3.amazonaws.com/Art/EOLE/CARDS/ALT_EOLE_B_AX_115/UNIQUE/JPG/en_US/ee4abd80beb562cb1a6458abed06b409.jpg",
            "isBanned": false,
            "isErrated": false,
            "isOwnerless": false,
            "isParentSerialized": false,
            "isSerialized": false,
            "isSuspended": false,
            "loreEntries": [],
            "lowerPrice": 0,
            "mainFaction": {
                "@id": "/factions/AX",
                "@type": "Faction",
                "color": "#8c432a",
                "id": "01GE7AC9XBG707G19F03A95TH1",
                "name": "Axiom",
                "reference": "AX"
            },
            "name": "Inari, Geist des Schaffens",
            "qrUrlDetail": "https://qr.altered.gg/ALT_EOLE_B_AX_115_U_139",
            "rarity": {
                "@id": "/.well-known/genid/5fa77d3f4e61884aba3d",
                "@type": "Rarity",
                "id": "01GE7AC9X35JXEQZJBBD6E4BKW",
                "name": "Unique",
                "reference": "UNIQUE"
            },
            "reference": "ALT_EOLE_B_AX_115_U_139"
        },
        "es-es": {
            "@context": "/contexts/Card",
            "@id": "/cards/ALT_EOLE_B_AX_115_U_139",
            "@type": "Card",
            "allImagePath": {
                "de-de": "",
                "en-us": "https://altered-prod-eu.s3.amazonaws.com/Art/EOLE/CARDS/ALT_EOLE_B_AX_115/UNIQUE/JPG/en_US/ee4abd80beb562cb1a6458abed06b409.jpg",
                "es-es": "",
                "fr-fr": "https://altered-prod-eu.s3.amazonaws.com/Art/EOLE/CARDS/ALT_EOLE_B_AX_115/UNIQUE/JPG/fr_FR/1f3f15fd6e1a168a89ac07073b2ce27a.jpg",
                "it-it": ""
            },
            "assets": {
                "WEB": [
                    "https://altered-prod-eu.s3.amazonaws.com/Art/EOLE/CARDS/ALT_EOLE_B_AX_115/WEB_016fd1f40f65ce5bdc99f4b762431413",
                    "https://altered-prod-eu.s3.amazonaws.com/Art/EOLE/CARDS/ALT_EOLE_B_AX_115/WEB_c55528c8b3468d929bc8cba1fb00348b",
                    "https://altered-prod-eu.s3.amazonaws.com/Art/EOLE/CARDS/ALT_EOLE_B_AX_115/WEB_289e3ffb45a1e9035052e04ae38e1c25"
                ]
            },
            "cardSet": {
                "@id": "/card_sets/EOLE",
                "@type": "CardSet",
                "id": "01K9YWHXF2T6GJJDWAK333TJGV",
                "name": "Roots of Corruption",
                "reference": "EOLE"
            },
            "cardSubTypes": [
                {
                    "@id": "/.well-known/genid/58c31416f8e686cc04b9",
                    "@type": "CardSubType",
                    "id": "01HKAGPDNDJM76PRKTBB98Q0ZM",
                    "name": "Robot",
                    "reference": "ROBOT"
                },
                {
                    "@id": "/.well-known/genid/0ca1af71528e2b157816",
                    "@type": "CardSubType",
                    "id": "01HKAGPAJFS4YDQVKY6AB16614",
                    "name": "Deidad",
                    "reference": "DEITY"
                }
            ],
            "cardType": {
                "@id": "/card_types/01H19NWA92A4ERAC4ATMSZNASS",
                "@type": "CardType",
                "id": "01H19NWA92A4ERAC4ATMSZNASS",
                "name": "Personaje",
                "reference": "CHARACTER"
            },
            "elements": {
                "ECHO_EFFECT": "{D} : []El siguiente personaje que juegues desde tu mano este turno activa una de sus habilidades {r}.",
                "FOREST_POWER": "5",
                "MAIN_COST": "4",
                "MAIN_EFFECT": "Cuando pases — Si tu mano está vacía: Roba dos cartas.  Cuando abandone la zona de expedición, si tenía [[Fugacidad]] — []Crea dos fichas de [Aerolito] en tus hitos.",
                "MOUNTAIN_POWER": "3",
                "OCEAN_POWER": "5",
                "RECALL_COST": "4"
            },
            "id": "4FSE7996C49KFV456HTYE0BQ3M",
            "imagePath": "https://altered-prod-eu.s3.amazonaws.com/Art/EOLE/CARDS/ALT_EOLE_B_AX_115/UNIQUE/JPG/en_US/ee4abd80beb562cb1a6458abed06b409.jpg",
            "isBanned": false,
            "isErrated": false,
            "isOwnerless": false,
            "isParentSerialized": false,
            "isSerialized": false,
            "isSuspended": false,
            "loreEntries": [],
            "lowerPrice": 0,
            "mainFaction": {
                "@id": "/factions/AX",
                "@type": "Faction",
                "color": "#8c432a",
                "id": "01GE7AC9XBG707G19F03A95TH1",
                "name": "Axiom",
                "reference": "AX"
            },
            "name": "Inari, espíritu de la industria",
            "qrUrlDetail": "https://qr.altered.gg/ALT_EOLE_B_AX_115_U_139",
            "rarity": {
                "@id": "/.well-known/genid/b610b02038f345bc9ac3",
                "@type": "Rarity",
                "id": "01GE7AC9X35JXEQZJBBD6E4BKW",
                "name": "Unique",
                "reference": "UNIQUE"
            },
            "reference": "ALT_EOLE_B_AX_115_U_139"
        },
        "fr-fr": {
            "@context": "/contexts/Card",
            "@id": "/cards/ALT_EOLE_B_AX_115_U_139",
            "@type": "Card",
            "allImagePath": {
                "de-de": "",
                "en-us": "https://altered-prod-eu.s3.amazonaws.com/Art/EOLE/CARDS/ALT_EOLE_B_AX_115/UNIQUE/JPG/en_US/ee4abd80beb562cb1a6458abed06b409.jpg",
                "es-es": "",
                "fr-fr": "https://altered-prod-eu.s3.amazonaws.com/Art/EOLE/CARDS/ALT_EOLE_B_AX_115/UNIQUE/JPG/fr_FR/1f3f15fd6e1a168a89ac07073b2ce27a.jpg",
                "it-it": ""
            },
            "assets": {
                "WEB": [
                    "https://altered-prod-eu.s3.amazonaws.com/Art/EOLE/CARDS/ALT_EOLE_B_AX_115/WEB_016fd1f40f65ce5bdc99f4b762431413",
                    "https://altered-prod-eu.s3.amazonaws.com/Art/EOLE/CARDS/ALT_EOLE_B_AX_115/WEB_c55528c8b3468d929bc8cba1fb00348b",
                    "https://altered-prod-eu.s3.amazonaws.com/Art/EOLE/CARDS/ALT_EOLE_B_AX_115/WEB_289e3ffb45a1e9035052e04ae38e1c25"
                ]
            },
            "cardSet": {
                "@id": "/card_sets/EOLE",
                "@type": "CardSet",
                "id": "01K9YWHXF2T6GJJDWAK333TJGV",
                "name": "Les Racines de la Corruption",
                "reference": "EOLE"
            },
            "cardSubTypes": [
                {
                    "@id": "/.well-known/genid/6bb1e678898f5feac203",
                    "@type": "CardSubType",
                    "id": "01HKAGPDNDJM76PRKTBB98Q0ZM",
                    "name": "Robot",
                    "reference": "ROBOT"
                },
                {
                    "@id": "/.well-known/genid/1cbf02df64753c0dbb8b",
                    "@type": "CardSubType",
                    "id": "01HKAGPAJFS4YDQVKY6AB16614",
                    "name": "Divinité",
                    "reference": "DEITY"
                }
            ],
            "cardType": {
                "@id": "/card_types/01H19NWA92A4ERAC4ATMSZNASS",
                "@type": "CardType",
                "id": "01H19NWA92A4ERAC4ATMSZNASS",
                "name": "Personnage",
                "reference": "CHARACTER"
            },
            "elements": {
                "ECHO_EFFECT": "{D} : []Le prochain Personnage joué de votre main ce tour-ci active l'une de ses capacités {r}.",
                "FOREST_POWER": "5",
                "MAIN_COST": "4",
                "MAIN_EFFECT": "Lorsque vous passez — Si votre main est vide : Piochez deux cartes.  Lorsque je quitte la zone d'Expédition, si j'étais [[Fugace]] — []Créez deux jetons [Aérolithe] dans vos Repères.",
                "MOUNTAIN_POWER": "3",
                "OCEAN_POWER": "5",
                "RECALL_COST": "4"
            },
            "id": "4FSE7996C49KFV456HTYE0BQ3M",
            "imagePath": "https://altered-prod-eu.s3.amazonaws.com/Art/EOLE/CARDS/ALT_EOLE_B_AX_115/UNIQUE/JPG/fr_FR/1f3f15fd6e1a168a89ac07073b2ce27a.jpg",
            "isBanned": false,
            "isErrated": false,
            "isOwnerless": false,
            "isParentSerialized": false,
            "isSerialized": false,
            "isSuspended": false,
            "loreEntries": [],
            "lowerPrice": 0,
            "mainFaction": {
                "@id": "/factions/AX",
                "@type": "Faction",
                "color": "#8c432a",
                "id": "01GE7AC9XBG707G19F03A95TH1",
                "name": "Axiom",
                "reference": "AX"
            },
            "name": "Inari, Esprit de l'Industrie",
            "qrUrlDetail": "https://qr.altered.gg/ALT_EOLE_B_AX_115_U_139",
            "rarity": {
                "@id": "/.well-known/genid/b171abefb8d6491b387c",
                "@type": "Rarity",
                "id": "01GE7AC9X35JXEQZJBBD6E4BKW",
                "name": "Unique",
                "reference": "UNIQUE"
            },
            "reference": "ALT_EOLE_B_AX_115_U_139"
        },
        "it-it": {
            "@context": "/contexts/Card",
            "@id": "/cards/ALT_EOLE_B_AX_115_U_139",
            "@type": "Card",
            "allImagePath": {
                "de-de": "",
                "en-us": "https://altered-prod-eu.s3.amazonaws.com/Art/EOLE/CARDS/ALT_EOLE_B_AX_115/UNIQUE/JPG/en_US/ee4abd80beb562cb1a6458abed06b409.jpg",
                "es-es": "",
                "fr-fr": "https://altered-prod-eu.s3.amazonaws.com/Art/EOLE/CARDS/ALT_EOLE_B_AX_115/UNIQUE/JPG/fr_FR/1f3f15fd6e1a168a89ac07073b2ce27a.jpg",
                "it-it": ""
            },
            "assets": {
                "WEB": [
                    "https://altered-prod-eu.s3.amazonaws.com/Art/EOLE/CARDS/ALT_EOLE_B_AX_115/WEB_016fd1f40f65ce5bdc99f4b762431413",
                    "https://altered-prod-eu.s3.amazonaws.com/Art/EOLE/CARDS/ALT_EOLE_B_AX_115/WEB_c55528c8b3468d929bc8cba1fb00348b",
                    "https://altered-prod-eu.s3.amazonaws.com/Art/EOLE/CARDS/ALT_EOLE_B_AX_115/WEB_289e3ffb45a1e9035052e04ae38e1c25"
                ]
            },
            "cardSet": {
                "@id": "/card_sets/EOLE",
                "@type": "CardSet",
                "id": "01K9YWHXF2T6GJJDWAK333TJGV",
                "name": "Roots of Corruption",
                "reference": "EOLE"
            },
            "cardSubTypes": [
                {
                    "@id": "/.well-known/genid/7e01cd23858ed4215d62",
                    "@type": "CardSubType",
                    "id": "01HKAGPDNDJM76PRKTBB98Q0ZM",
                    "name": "Robot",
                    "reference": "ROBOT"
                },
                {
                    "@id": "/.well-known/genid/ade3eb3059504b69d812",
                    "@type": "CardSubType",
                    "id": "01HKAGPAJFS4YDQVKY6AB16614",
                    "name": "Divinità",
                    "reference": "DEITY"
                }
            ],
            "cardType": {
                "@id": "/card_types/01H19NWA92A4ERAC4ATMSZNASS",
                "@type": "CardType",
                "id": "01H19NWA92A4ERAC4ATMSZNASS",
                "name": "Personaggio",
                "reference": "CHARACTER"
            },
            "elements": {
                "ECHO_EFFECT": "{D}: []Il prossimo personaggio giocato dalla tua mano in questo turno attiva una delle sue abilità {r}.",
                "FOREST_POWER": "5",
                "MAIN_COST": "4",
                "MAIN_EFFECT": "Quando passi — Se la tua mano è vuota: Pesca due carte.  Quando lascio l'area delle spedizioni, se avevo [[Fugace]] — []Crea due pedine [Aerolite] nei tuoi fulcri.",
                "MOUNTAIN_POWER": "3",
                "OCEAN_POWER": "5",
                "RECALL_COST": "4"
            },
            "id": "4FSE7996C49KFV456HTYE0BQ3M",
            "imagePath": "https://altered-prod-eu.s3.amazonaws.com/Art/EOLE/CARDS/ALT_EOLE_B_AX_115/UNIQUE/JPG/en_US/ee4abd80beb562cb1a6458abed06b409.jpg",
            "isBanned": false,
            "isErrated": false,
            "isOwnerless": false,
            "isParentSerialized": false,
            "isSerialized": false,
            "isSuspended": false,
            "loreEntries": [],
            "lowerPrice": 0,
            "mainFaction": {
                "@id": "/factions/AX",
                "@type": "Faction",
                "color": "#8c432a",
                "id": "01GE7AC9XBG707G19F03A95TH1",
                "name": "Axiom",
                "reference": "AX"
            },
            "name": "Inari, Spirito dell'Industria",
            "qrUrlDetail": "https://qr.altered.gg/ALT_EOLE_B_AX_115_U_139",
            "rarity": {
                "@id": "/.well-known/genid/70200a38d8adfd822203",
                "@type": "Rarity",
                "id": "01GE7AC9X35JXEQZJBBD6E4BKW",
                "name": "Unique",
                "reference": "UNIQUE"
            },
            "reference": "ALT_EOLE_B_AX_115_U_139"
        }
    }
}