{
    "@context": "/contexts/Card",
    "@id": "/cards/ALT_CYCLONE_B_LY_71_U_10160",
    "@type": "Card",
    "allImagePath": {
        "de-de": "",
        "en-us": "https://altered-prod-eu.s3.amazonaws.com/Art/CYCLONE/CARDS/ALT_CYCLONE_B_LY_71/UNIQUE/JPG/en_US/7d0493e3a816c18c57588d73224c3786.jpg",
        "es-es": "",
        "fr-fr": "https://altered-prod-eu.s3.amazonaws.com/Art/CYCLONE/CARDS/ALT_CYCLONE_B_LY_71/UNIQUE/JPG/fr_FR/0ca4afa2102972b99c8dd0388d3c113c.jpg",
        "it-it": ""
    },
    "assets": {
        "WEB": [
            "https://altered-prod-eu.s3.amazonaws.com/Art/CYCLONE/CARDS/ALT_CYCLONE_B_LY_71/WEB_efd11788065e2beb5699398e7857924f",
            "https://altered-prod-eu.s3.amazonaws.com/Art/CYCLONE/CARDS/ALT_CYCLONE_B_LY_71/WEB_ae278649ab2a058fcee8ea24c8dcfab6",
            "https://altered-prod-eu.s3.amazonaws.com/Art/CYCLONE/CARDS/ALT_CYCLONE_B_LY_71/WEB_84ff8d93cfb26d30d01efef8382ec7db"
        ]
    },
    "cardSet": {
        "@id": "/card_sets/CYCLONE",
        "@type": "CardSet",
        "id": "01JN9HN8N6WR959TS2XEJWWZ4P",
        "name": "Skybound Odyssey",
        "reference": "CYCLONE"
    },
    "cardSubTypes": [
        {
            "@id": "/.well-known/genid/d5b7fd9e58e87d7f8359",
            "@type": "CardSubType",
            "id": "01HKAGPBKC6V2RK28EZGHP8VWW",
            "name": "Fairy",
            "reference": "FAIRY"
        }
    ],
    "cardType": {
        "@id": "/card_types/01H19NWA92A4ERAC4ATMSZNASS",
        "@type": "CardType",
        "id": "01H19NWA92A4ERAC4ATMSZNASS",
        "name": "Character",
        "reference": "CHARACTER"
    },
    "elements": {
        "ECHO_EFFECT": "{D} : []Pay {1} less for the next Character you play this turn.",
        "FOREST_POWER": "3",
        "MAIN_COST": "2",
        "MAIN_EFFECT": "{J} If there are two or more cards in your Reserve: Target Character gains 1 boost.  {R} If I'm facing an Expedition in {V}: [Resupply], otherwise each player [Resupplies].",
        "MOUNTAIN_POWER": "0",
        "OCEAN_POWER": "0",
        "RECALL_COST": "2"
    },
    "id": "1H7BHDE5388CQAD8S0QXJQJR7B",
    "imagePath": "https://altered-prod-eu.s3.amazonaws.com/Art/CYCLONE/CARDS/ALT_CYCLONE_B_LY_71/UNIQUE/JPG/en_US/7d0493e3a816c18c57588d73224c3786.jpg",
    "isBanned": false,
    "isErrated": false,
    "isOwnerless": false,
    "isParentSerialized": false,
    "isSerialized": false,
    "isSuspended": false,
    "loreEntries": [],
    "lowerPrice": 0,
    "mainFaction": {
        "@id": "/factions/MU",
        "@type": "Faction",
        "color": "#3d6b42",
        "id": "01GE7AC9X2BNM40TTAYAEFSZSJ",
        "name": "Muna",
        "reference": "MU"
    },
    "name": "Forest Nymph",
    "qrUrlDetail": "https://qr.altered.gg/ALT_CYCLONE_B_LY_71_U_10160",
    "rarity": {
        "@id": "/.well-known/genid/7c9f332d6c772083d441",
        "@type": "Rarity",
        "id": "01GE7AC9X35JXEQZJBBD6E4BKW",
        "name": "Unique",
        "reference": "UNIQUE"
    },
    "reference": "ALT_CYCLONE_B_LY_71_U_10160",
    "translations": {
        "de-de": {
            "@context": "/contexts/Card",
            "@id": "/cards/ALT_CYCLONE_B_LY_71_U_10160",
            "@type": "Card",
            "allImagePath": {
                "de-de": "",
                "en-us": "https://altered-prod-eu.s3.amazonaws.com/Art/CYCLONE/CARDS/ALT_CYCLONE_B_LY_71/UNIQUE/JPG/en_US/7d0493e3a816c18c57588d73224c3786.jpg",
                "es-es": "",
                "fr-fr": "https://altered-prod-eu.s3.amazonaws.com/Art/CYCLONE/CARDS/ALT_CYCLONE_B_LY_71/UNIQUE/JPG/fr_FR/0ca4afa2102972b99c8dd0388d3c113c.jpg",
                "it-it": ""
            },
            "assets": {
                "WEB": [
                    "https://altered-prod-eu.s3.amazonaws.com/Art/CYCLONE/CARDS/ALT_CYCLONE_B_LY_71/WEB_efd11788065e2beb5699398e7857924f",
                    "https://altered-prod-eu.s3.amazonaws.com/Art/CYCLONE/CARDS/ALT_CYCLONE_B_LY_71/WEB_ae278649ab2a058fcee8ea24c8dcfab6",
                    "https://altered-prod-eu.s3.amazonaws.com/Art/CYCLONE/CARDS/ALT_CYCLONE_B_LY_71/WEB_84ff8d93cfb26d30d01efef8382ec7db"
                ]
            },
            "cardSet": {
                "@id": "/card_sets/CYCLONE",
                "@type": "CardSet",
                "id": "01JN9HN8N6WR959TS2XEJWWZ4P",
                "name": "Skybound Odyssey",
                "reference": "CYCLONE"
            },
            "cardSubTypes": [
                {
                    "@id": "/.well-known/genid/76f9019ef08b453335b4",
                    "@type": "CardSubType",
                    "id": "01HKAGPBKC6V2RK28EZGHP8VWW",
                    "name": "Fee",
                    "reference": "FAIRY"
                }
            ],
            "cardType": {
                "@id": "/card_types/01H19NWA92A4ERAC4ATMSZNASS",
                "@type": "CardType",
                "id": "01H19NWA92A4ERAC4ATMSZNASS",
                "name": "Charakter",
                "reference": "CHARACTER"
            },
            "elements": {
                "ECHO_EFFECT": "{D} : []Zahle {1} weniger für den nächsten Charakter, den du in dieser Runde spielst.",
                "FOREST_POWER": "3",
                "MAIN_COST": "2",
                "MAIN_EFFECT": "{J} Falls sich mindestens zwei Karten in deiner Reserve befinden: Ein Charakter deiner Wahl erhält 1 Verstärkung.  {R} Falls ich einer Expedition in {V} gegenüberstehe: [Nachschub], andernfalls nutzt jeder Spieler [Nachschub].",
                "MOUNTAIN_POWER": "0",
                "OCEAN_POWER": "0",
                "RECALL_COST": "2"
            },
            "id": "1H7BHDE5388CQAD8S0QXJQJR7B",
            "imagePath": "https://altered-prod-eu.s3.amazonaws.com/Art/CYCLONE/CARDS/ALT_CYCLONE_B_LY_71/UNIQUE/JPG/en_US/7d0493e3a816c18c57588d73224c3786.jpg",
            "isBanned": false,
            "isErrated": false,
            "isOwnerless": false,
            "isParentSerialized": false,
            "isSerialized": false,
            "isSuspended": false,
            "loreEntries": [],
            "lowerPrice": 0,
            "mainFaction": {
                "@id": "/factions/MU",
                "@type": "Faction",
                "color": "#3d6b42",
                "id": "01GE7AC9X2BNM40TTAYAEFSZSJ",
                "name": "Muna",
                "reference": "MU"
            },
            "name": "Waldnymphe",
            "qrUrlDetail": "https://qr.altered.gg/ALT_CYCLONE_B_LY_71_U_10160",
            "rarity": {
                "@id": "/.well-known/genid/7d49f8c7d3170cd5d9c2",
                "@type": "Rarity",
                "id": "01GE7AC9X35JXEQZJBBD6E4BKW",
                "name": "Unique",
                "reference": "UNIQUE"
            },
            "reference": "ALT_CYCLONE_B_LY_71_U_10160"
        },
        "es-es": {
            "@context": "/contexts/Card",
            "@id": "/cards/ALT_CYCLONE_B_LY_71_U_10160",
            "@type": "Card",
            "allImagePath": {
                "de-de": "",
                "en-us": "https://altered-prod-eu.s3.amazonaws.com/Art/CYCLONE/CARDS/ALT_CYCLONE_B_LY_71/UNIQUE/JPG/en_US/7d0493e3a816c18c57588d73224c3786.jpg",
                "es-es": "",
                "fr-fr": "https://altered-prod-eu.s3.amazonaws.com/Art/CYCLONE/CARDS/ALT_CYCLONE_B_LY_71/UNIQUE/JPG/fr_FR/0ca4afa2102972b99c8dd0388d3c113c.jpg",
                "it-it": ""
            },
            "assets": {
                "WEB": [
                    "https://altered-prod-eu.s3.amazonaws.com/Art/CYCLONE/CARDS/ALT_CYCLONE_B_LY_71/WEB_efd11788065e2beb5699398e7857924f",
                    "https://altered-prod-eu.s3.amazonaws.com/Art/CYCLONE/CARDS/ALT_CYCLONE_B_LY_71/WEB_ae278649ab2a058fcee8ea24c8dcfab6",
                    "https://altered-prod-eu.s3.amazonaws.com/Art/CYCLONE/CARDS/ALT_CYCLONE_B_LY_71/WEB_84ff8d93cfb26d30d01efef8382ec7db"
                ]
            },
            "cardSet": {
                "@id": "/card_sets/CYCLONE",
                "@type": "CardSet",
                "id": "01JN9HN8N6WR959TS2XEJWWZ4P",
                "name": "Skybound Odyssey",
                "reference": "CYCLONE"
            },
            "cardSubTypes": [
                {
                    "@id": "/.well-known/genid/14d336de380cf8384625",
                    "@type": "CardSubType",
                    "id": "01HKAGPBKC6V2RK28EZGHP8VWW",
                    "name": "Hada",
                    "reference": "FAIRY"
                }
            ],
            "cardType": {
                "@id": "/card_types/01H19NWA92A4ERAC4ATMSZNASS",
                "@type": "CardType",
                "id": "01H19NWA92A4ERAC4ATMSZNASS",
                "name": "Personaje",
                "reference": "CHARACTER"
            },
            "elements": {
                "ECHO_EFFECT": "{D} : []Paga {1} menos por el siguiente personaje que juegues este turno.",
                "FOREST_POWER": "3",
                "MAIN_COST": "2",
                "MAIN_EFFECT": "{J} Si tienes dos o más cartas en reserva: Un personaje objetivo gana 1 potenciador.  {R} Si la expedición enfrentada a mí está en {V}: [reabastece]. De lo contrario, cada jugador [reabastece].",
                "MOUNTAIN_POWER": "0",
                "OCEAN_POWER": "0",
                "RECALL_COST": "2"
            },
            "id": "1H7BHDE5388CQAD8S0QXJQJR7B",
            "imagePath": "https://altered-prod-eu.s3.amazonaws.com/Art/CYCLONE/CARDS/ALT_CYCLONE_B_LY_71/UNIQUE/JPG/en_US/7d0493e3a816c18c57588d73224c3786.jpg",
            "isBanned": false,
            "isErrated": false,
            "isOwnerless": false,
            "isParentSerialized": false,
            "isSerialized": false,
            "isSuspended": false,
            "loreEntries": [],
            "lowerPrice": 0,
            "mainFaction": {
                "@id": "/factions/MU",
                "@type": "Faction",
                "color": "#3d6b42",
                "id": "01GE7AC9X2BNM40TTAYAEFSZSJ",
                "name": "Muna",
                "reference": "MU"
            },
            "name": "Ninfa del bosque",
            "qrUrlDetail": "https://qr.altered.gg/ALT_CYCLONE_B_LY_71_U_10160",
            "rarity": {
                "@id": "/.well-known/genid/1ee4c24c9246cd0cda73",
                "@type": "Rarity",
                "id": "01GE7AC9X35JXEQZJBBD6E4BKW",
                "name": "Unique",
                "reference": "UNIQUE"
            },
            "reference": "ALT_CYCLONE_B_LY_71_U_10160"
        },
        "fr-fr": {
            "@context": "/contexts/Card",
            "@id": "/cards/ALT_CYCLONE_B_LY_71_U_10160",
            "@type": "Card",
            "allImagePath": {
                "de-de": "",
                "en-us": "https://altered-prod-eu.s3.amazonaws.com/Art/CYCLONE/CARDS/ALT_CYCLONE_B_LY_71/UNIQUE/JPG/en_US/7d0493e3a816c18c57588d73224c3786.jpg",
                "es-es": "",
                "fr-fr": "https://altered-prod-eu.s3.amazonaws.com/Art/CYCLONE/CARDS/ALT_CYCLONE_B_LY_71/UNIQUE/JPG/fr_FR/0ca4afa2102972b99c8dd0388d3c113c.jpg",
                "it-it": ""
            },
            "assets": {
                "WEB": [
                    "https://altered-prod-eu.s3.amazonaws.com/Art/CYCLONE/CARDS/ALT_CYCLONE_B_LY_71/WEB_efd11788065e2beb5699398e7857924f",
                    "https://altered-prod-eu.s3.amazonaws.com/Art/CYCLONE/CARDS/ALT_CYCLONE_B_LY_71/WEB_ae278649ab2a058fcee8ea24c8dcfab6",
                    "https://altered-prod-eu.s3.amazonaws.com/Art/CYCLONE/CARDS/ALT_CYCLONE_B_LY_71/WEB_84ff8d93cfb26d30d01efef8382ec7db"
                ]
            },
            "cardSet": {
                "@id": "/card_sets/CYCLONE",
                "@type": "CardSet",
                "id": "01JN9HN8N6WR959TS2XEJWWZ4P",
                "name": "Odyssée des cieux",
                "reference": "CYCLONE"
            },
            "cardSubTypes": [
                {
                    "@id": "/.well-known/genid/0dbc423cd2d12e94710f",
                    "@type": "CardSubType",
                    "id": "01HKAGPBKC6V2RK28EZGHP8VWW",
                    "name": "Fée",
                    "reference": "FAIRY"
                }
            ],
            "cardType": {
                "@id": "/card_types/01H19NWA92A4ERAC4ATMSZNASS",
                "@type": "CardType",
                "id": "01H19NWA92A4ERAC4ATMSZNASS",
                "name": "Personnage",
                "reference": "CHARACTER"
            },
            "elements": {
                "ECHO_EFFECT": "{D} : []Payez {1} de moins pour le prochain Personnage que vous jouez ce tour-ci.",
                "FOREST_POWER": "3",
                "MAIN_COST": "2",
                "MAIN_EFFECT": "{J} S'il y a au moins deux cartes dans votre Réserve : Un Personnage ciblé gagne 1 boost.  {R} Si je suis face à une Expédition en {V} : [Ravitaillez]. Sinon, chaque joueur [Ravitaille].",
                "MOUNTAIN_POWER": "0",
                "OCEAN_POWER": "0",
                "RECALL_COST": "2"
            },
            "id": "1H7BHDE5388CQAD8S0QXJQJR7B",
            "imagePath": "https://altered-prod-eu.s3.amazonaws.com/Art/CYCLONE/CARDS/ALT_CYCLONE_B_LY_71/UNIQUE/JPG/fr_FR/0ca4afa2102972b99c8dd0388d3c113c.jpg",
            "isBanned": false,
            "isErrated": false,
            "isOwnerless": false,
            "isParentSerialized": false,
            "isSerialized": false,
            "isSuspended": false,
            "loreEntries": [],
            "lowerPrice": 0,
            "mainFaction": {
                "@id": "/factions/MU",
                "@type": "Faction",
                "color": "#3d6b42",
                "id": "01GE7AC9X2BNM40TTAYAEFSZSJ",
                "name": "Muna",
                "reference": "MU"
            },
            "name": "Nymphe des Forêts",
            "qrUrlDetail": "https://qr.altered.gg/ALT_CYCLONE_B_LY_71_U_10160",
            "rarity": {
                "@id": "/.well-known/genid/41c6bbddfd748a91e1f6",
                "@type": "Rarity",
                "id": "01GE7AC9X35JXEQZJBBD6E4BKW",
                "name": "Unique",
                "reference": "UNIQUE"
            },
            "reference": "ALT_CYCLONE_B_LY_71_U_10160"
        },
        "it-it": {
            "@context": "/contexts/Card",
            "@id": "/cards/ALT_CYCLONE_B_LY_71_U_10160",
            "@type": "Card",
            "allImagePath": {
                "de-de": "",
                "en-us": "https://altered-prod-eu.s3.amazonaws.com/Art/CYCLONE/CARDS/ALT_CYCLONE_B_LY_71/UNIQUE/JPG/en_US/7d0493e3a816c18c57588d73224c3786.jpg",
                "es-es": "",
                "fr-fr": "https://altered-prod-eu.s3.amazonaws.com/Art/CYCLONE/CARDS/ALT_CYCLONE_B_LY_71/UNIQUE/JPG/fr_FR/0ca4afa2102972b99c8dd0388d3c113c.jpg",
                "it-it": ""
            },
            "assets": {
                "WEB": [
                    "https://altered-prod-eu.s3.amazonaws.com/Art/CYCLONE/CARDS/ALT_CYCLONE_B_LY_71/WEB_efd11788065e2beb5699398e7857924f",
                    "https://altered-prod-eu.s3.amazonaws.com/Art/CYCLONE/CARDS/ALT_CYCLONE_B_LY_71/WEB_ae278649ab2a058fcee8ea24c8dcfab6",
                    "https://altered-prod-eu.s3.amazonaws.com/Art/CYCLONE/CARDS/ALT_CYCLONE_B_LY_71/WEB_84ff8d93cfb26d30d01efef8382ec7db"
                ]
            },
            "cardSet": {
                "@id": "/card_sets/CYCLONE",
                "@type": "CardSet",
                "id": "01JN9HN8N6WR959TS2XEJWWZ4P",
                "name": "Skybound Odyssey",
                "reference": "CYCLONE"
            },
            "cardSubTypes": [
                {
                    "@id": "/.well-known/genid/193acaf7e967435f9466",
                    "@type": "CardSubType",
                    "id": "01HKAGPBKC6V2RK28EZGHP8VWW",
                    "name": "Folletto",
                    "reference": "FAIRY"
                }
            ],
            "cardType": {
                "@id": "/card_types/01H19NWA92A4ERAC4ATMSZNASS",
                "@type": "CardType",
                "id": "01H19NWA92A4ERAC4ATMSZNASS",
                "name": "Personaggio",
                "reference": "CHARACTER"
            },
            "elements": {
                "ECHO_EFFECT": "{D}: []Paga {1} in meno per il prossimo personaggio che giochi in questo turno.",
                "FOREST_POWER": "3",
                "MAIN_COST": "2",
                "MAIN_EFFECT": "{J} Se ci sono due o più carte nella tua Riserva: Un personaggio bersaglio ottiene 1 rinforzo.  {R} Se sto affrontando una spedizione in {V}: [Rifornisci], altrimenti ogni giocatore [Rifornisce].",
                "MOUNTAIN_POWER": "0",
                "OCEAN_POWER": "0",
                "RECALL_COST": "2"
            },
            "id": "1H7BHDE5388CQAD8S0QXJQJR7B",
            "imagePath": "https://altered-prod-eu.s3.amazonaws.com/Art/CYCLONE/CARDS/ALT_CYCLONE_B_LY_71/UNIQUE/JPG/en_US/7d0493e3a816c18c57588d73224c3786.jpg",
            "isBanned": false,
            "isErrated": false,
            "isOwnerless": false,
            "isParentSerialized": false,
            "isSerialized": false,
            "isSuspended": false,
            "loreEntries": [],
            "lowerPrice": 0,
            "mainFaction": {
                "@id": "/factions/MU",
                "@type": "Faction",
                "color": "#3d6b42",
                "id": "01GE7AC9X2BNM40TTAYAEFSZSJ",
                "name": "Muna",
                "reference": "MU"
            },
            "name": "Ninfa della Foresta",
            "qrUrlDetail": "https://qr.altered.gg/ALT_CYCLONE_B_LY_71_U_10160",
            "rarity": {
                "@id": "/.well-known/genid/412761844fb72afa3cbf",
                "@type": "Rarity",
                "id": "01GE7AC9X35JXEQZJBBD6E4BKW",
                "name": "Unique",
                "reference": "UNIQUE"
            },
            "reference": "ALT_CYCLONE_B_LY_71_U_10160"
        }
    },
    "updated": "2026-03-31 23:36:25"
}